vame/__init__.py
vame/pipeline.py
vame/analysis/__init__.py
vame/analysis/community_analysis.py
vame/analysis/generative_functions.py
vame/analysis/gif_creator.py
vame/analysis/pose_segmentation.py
vame/analysis/tree_hierarchy.py
vame/analysis/videowriter.py
vame/initialize_project/__init__.py
vame/initialize_project/new.py
vame/io/__init__.py
vame/io/load_poses.py
vame/io/nwb.py
vame/logging/logger.py
vame/model/__init__.py
vame/model/create_training.py
vame/model/dataloader.py
vame/model/evaluate.py
vame/model/rnn_model.py
vame/model/rnn_vae.py
vame/preprocessing/__init__.py
vame/preprocessing/align_egocentrical_legacy.py
vame/preprocessing/alignment.py
vame/preprocessing/cleaning.py
vame/preprocessing/filter.py
vame/preprocessing/inspection.py
vame/preprocessing/preprocessing.py
vame/preprocessing/scaling.py
vame/preprocessing/to_model.py
vame/schemas/project.py
vame/schemas/states.py
vame/util/__init__.py
vame/util/auxiliary.py
vame/util/cli.py
vame/util/csv_to_npy.py
vame/util/data_manipulation.py
vame/util/gif_pose_helper.py
vame/util/model_util.py
vame/util/sample_data.py
vame/video/__init__.py
vame/video/video.py
vame/visualization/__init__.py
vame/visualization/community.py
vame/visualization/model.py
vame/visualization/motif.py
vame/visualization/preprocessing.py
vame/visualization/report.py
vame/visualization/umap.py
vame_py-0.12.0.dist-info/licenses/LICENSE
vame_py-0.12.0.dist-info/METADATA
vame_py-0.12.0.dist-info/WHEEL
vame_py-0.12.0.dist-info/top_level.txt
vame_py-0.12.0.dist-info/RECORD
