Metadata-Version: 2.4
Name: vame-py
Version: 0.12.0
Summary: Variational Animal Motion Embedding.
Author: K. Luxem & , P. Bauer
Project-URL: homepage, https://github.com/EthoML/VAME/
Project-URL: repository, https://github.com/EthoML/VAME/
Keywords: vame,auto-encoder
Requires-Python: >=3.11
License-File: LICENSE
Requires-Dist: PyYAML>=6.0.0
Requires-Dist: ruamel.yaml>=0.18.0
Requires-Dist: numpy>=2.2.0
Requires-Dist: pandas>=2.2.0
Requires-Dist: scipy>=1.13.0
Requires-Dist: matplotlib>=3.9.0
Requires-Dist: plotly>=6.0.0
Requires-Dist: nbformat>=5.10.0
Requires-Dist: torch>=2.3.1; platform_system == "Darwin" and platform_machine == "arm64"
Requires-Dist: torch>=2.3.1; platform_system != "Darwin"
Requires-Dist: tensorboard
Requires-Dist: tqdm>=4.66.0
Requires-Dist: hmmlearn>=0.3.0
Requires-Dist: opencv-python-headless>=4.9.0.0
Requires-Dist: umap-learn>=0.5.8
Requires-Dist: numba>=0.61.2
Requires-Dist: contourpy>=1.3.0
Requires-Dist: h5py>=3.11.0
Requires-Dist: pydantic>=2.7.4
Requires-Dist: imageio==2.34.1
Requires-Dist: imageio-ffmpeg==0.5.1
Requires-Dist: pynwb==3.0.0
Requires-Dist: ndx-pose==0.2.2
Requires-Dist: ndx-vame==0.2.2
Requires-Dist: tables>=3.10.0
Requires-Dist: movement==0.7.1
Requires-Dist: netCDF4>=1.7.2
Dynamic: license-file
